{
  "openapi": "3.1.0",
  "info": {
    "title": "REQ-0036 Booking Changes",
    "version": "1.0.0"
  },
  "paths": {
    "/bookings/{bookingId}": {
      "patch": {
        "operationId": "updateBooking",
        "summary": "修改预约时间",
        "parameters": [
          {
            "name": "bookingId",
            "in": "path",
            "required": true,
            "schema": { "type": "string", "format": "uuid" }
          }
        ],
        "requestBody": {
          "required": true,
          "content": {
            "application/json": {
              "schema": { "$ref": "#/components/schemas/UpdateBookingRequest" }
            }
          }
        },
        "responses": {
          "200": { "description": "修改成功" },
          "409": { "description": "时间不可用" }
        }
      },
      "delete": {
        "operationId": "cancelBooking",
        "summary": "取消预约",
        "parameters": [
          {
            "name": "bookingId",
            "in": "path",
            "required": true,
            "schema": { "type": "string", "format": "uuid" }
          }
        ],
        "responses": {
          "204": { "description": "取消成功" },
          "409": { "description": "预约不能取消" }
        }
      }
    }
  },
  "components": {
    "schemas": {
      "UpdateBookingRequest": {
        "type": "object",
        "required": ["startsAt", "idempotencyKey"],
        "properties": {
          "startsAt": { "type": "string", "format": "date-time" },
          "idempotencyKey": { "type": "string", "minLength": 8 }
        }
      }
    }
  },
  "x-handover": { "remove": [] }
}
